setup.py
EasyPro/__init__.py
EasyPro/compile.py
EasyPro/disp_tool.py
EasyPro/file_version_control.py
EasyPro/matlab.py
EasyPro/path_tool.py
EasyPro/project.py
EasyPro.egg-info/PKG-INFO
EasyPro.egg-info/SOURCES.txt
EasyPro.egg-info/dependency_links.txt
EasyPro.egg-info/top_level.txt