Metadata-Version: 2.1
Name: EasyPro
Version: 39.2024.1.16.15.59
Summary: A python lib for xxxxx
Home-page: http://www.xxxxx.com/
Author: Quanfa
Author-email: quanfa@tju.edu.cn
License: MIT
